AUTHORS.rst
LICENSE
MANIFEST.in
README.rst
setup.py
snake_guice.egg-info/PKG-INFO
snake_guice.egg-info/SOURCES.txt
snake_guice.egg-info/dependency_links.txt
snake_guice.egg-info/top_level.txt
snakeguice/__init__.py
snakeguice/__pkginfo__.py
snakeguice/annotation.py
snakeguice/assist.py
snakeguice/bikes.py
snakeguice/binder.py
snakeguice/config.py
snakeguice/decorators.py
snakeguice/errors.py
snakeguice/injector.py
snakeguice/interceptors.py
snakeguice/interfaces.py
snakeguice/modules.py
snakeguice/multibinder.py
snakeguice/providers.py
snakeguice/scopes.py