Metadata-Version: 1.1
Name: snake-guice
Version: 0.5a1
Summary: A simple, lightweight Python dependency injection framework
Home-page: https://github.com/dstanek/snake-guice
Author: David Stanek
Author-email: dstanek@dstanek.com
License: MIT
Platform: UNKNOWN
Classifier: Development Status :: 4 - Beta
Classifier: Intended Audience :: Developers
Classifier: License :: OSI Approved :: MIT License
Classifier: Operating System :: OS Independent
Classifier: Programming Language :: Python
Classifier: Topic :: Software Development :: Libraries :: Python Modules
Classifier: Topic :: Software Development :: Libraries :: Application Frameworks
